MANIFEST.in
README.rst
setup.cfg
setup.py
versioneer.py
get_image_size/__init__.py
get_image_size/_version.py
opsdroid_get_image_size.egg-info/PKG-INFO
opsdroid_get_image_size.egg-info/SOURCES.txt
opsdroid_get_image_size.egg-info/dependency_links.txt
opsdroid_get_image_size.egg-info/entry_points.txt
opsdroid_get_image_size.egg-info/top_level.txt