Metadata-Version: 1.0
Name: opsdroid-get-image-size
Version: 0.2.2
Summary: UNKNOWN
Home-page: https://github.com/opsdroid/image_size
Author: github.com/scardine
Author-email:  
License: MIT
Platform: UNKNOWN
